README.md
setup.py
src/wmpaws/__init__.py
src/wmpaws.egg-info/PKG-INFO
src/wmpaws.egg-info/SOURCES.txt
src/wmpaws.egg-info/dependency_links.txt
src/wmpaws.egg-info/not-zip-safe
src/wmpaws.egg-info/requires.txt
src/wmpaws.egg-info/top_level.txt