Metadata-Version: 2.1
Name: wmpaws
Version: 1.0
Summary: A library for Wikimedia's PAWS service.
Home-page: UNKNOWN
Author: Martin Urbanec
Author-email: martin@urbanec.cz
License: GNU
Platform: any
Classifier: Intended Audience :: Developers
Classifier: License :: OSI Approved :: GNU General Public License v3 or later (GPLv3+)
Classifier: Operating System :: OS Independent
Classifier: Programming Language :: Python
Classifier: Topic :: Software Development :: Libraries :: Python Modules
